{
  "stat": "OK",
  "date": "20260210",
  "title": "115年02月10日 投信買賣超彙總表",
  "fields": [
    "",
    "證券代號",
    "證券名稱",
    "買進股數",
    "賣出股數",
    "買賣超股數"
  ],
  "data": [
    [
      " ",
      "0050  ",
      "元大台灣50      ",
      "4,526,000",
      "0",
      "4,526,000"
    ],
    [
      " ",
      "3037  ",
      "欣興            ",
      "3,415,000",
      "37,000",
      "3,378,000"
    ],
    [
      " ",
      "2885  ",
      "元大金          ",
      "1,814,000",
      "213,628",
      "1,600,372"
    ],
    [
      " ",
      "2344  ",
      "華邦電          ",
      "1,606,000",
      "33,000",
      "1,573,000"
    ],
    [
      " ",
      "2301  ",
      "光寶科          ",
      "1,479,000",
      "18,000",
      "1,461,000"
    ],
    [
      " ",
      "2337  ",
      "旺宏            ",
      "1,423,000",
      "0",
      "1,423,000"
    ],
    [
      " ",
      "2449  ",
      "京元電子        ",
      "1,283,000",
      "108,000",
      "1,175,000"
    ],
    [
      " ",
      "2345  ",
      "智邦            ",
      "910,000",
      "24,959",
      "885,041"
    ],
    [
      " ",
      "2886  ",
      "兆豐金          ",
      "936,000",
      "105,032",
      "830,968"
    ],
    [
      " ",
      "2368  ",
      "金像電          ",
      "750,000",
      "58,000",
      "692,000"
    ],
    [
      " ",
      "8046  ",
      "南電            ",
      "572,000",
      "0",
      "572,000"
    ],
    [
      " ",
      "3189  ",
      "景碩            ",
      "553,000",
      "3,000",
      "550,000"
    ],
    [
      " ",
      "2454  ",
      "聯發科          ",
      "592,900",
      "44,644",
      "548,256"
    ],
    [
      " ",
      "2377  ",
      "微星            ",
      "500,000",
      "0",
      "500,000"
    ],
    [
      " ",
      "2313  ",
      "華通            ",
      "607,000",
      "112,000",
      "495,000"
    ],
    [
      " ",
      "3167  ",
      "大量            ",
      "380,000",
      "0",
      "380,000"
    ],
    [
      " ",
      "8996  ",
      "高力            ",
      "287,000",
      "12,000",
      "275,000"
    ],
    [
      " ",
      "2385  ",
      "群光            ",
      "281,300",
      "12,592",
      "268,708"
    ],
    [
      " ",
      "2049  ",
      "上銀            ",
      "242,000",
      "1,282",
      "240,718"
    ],
    [
      " ",
      "2330  ",
      "台積電          ",
      "567,500",
      "326,858",
      "240,642"
    ],
    [
      " ",
      "4915  ",
      "致伸            ",
      "400,000",
      "167,000",
      "233,000"
    ],
    [
      " ",
      "2890  ",
      "永豐金          ",
      "340,000",
      "145,589",
      "194,411"
    ],
    [
      " ",
      "3005  ",
      "神基            ",
      "275,000",
      "113,002",
      "161,998"
    ],
    [
      " ",
      "0052  ",
      "富邦科技        ",
      "150,000",
      "0",
      "150,000"
    ],
    [
      " ",
      "3006  ",
      "晶豪科          ",
      "115,000",
      "0",
      "115,000"
    ],
    [
      " ",
      "6770  ",
      "力積電          ",
      "112,000",
      "0",
      "112,000"
    ],
    [
      " ",
      "5243  ",
      "乙盛-KY         ",
      "100,000",
      "0",
      "100,000"
    ],
    [
      " ",
      "2412  ",
      "中華電          ",
      "116,000",
      "19,000",
      "97,000"
    ],
    [
      " ",
      "3661  ",
      "世芯-KY         ",
      "90,000",
      "0",
      "90,000"
    ],
    [
      " ",
      "3665  ",
      "貿聯-KY         ",
      "170,000",
      "83,000",
      "87,000"
    ],
    [
      " ",
      "2383  ",
      "台光電          ",
      "118,000",
      "39,030",
      "78,970"
    ],
    [
      " ",
      "3406  ",
      "玉晶光          ",
      "73,000",
      "1,000",
      "72,000"
    ],
    [
      " ",
      "7769  ",
      "鴻勁            ",
      "52,300",
      "7,000",
      "45,300"
    ],
    [
      " ",
      "2645  ",
      "長榮航太        ",
      "45,000",
      "1,000",
      "44,000"
    ],
    [
      " ",
      "6515  ",
      "穎崴            ",
      "52,000",
      "9,000",
      "43,000"
    ],
    [
      " ",
      "2887F ",
      "台新新光戊特二  ",
      "30,000",
      "0",
      "30,000"
    ],
    [
      " ",
      "3004  ",
      "豐達科          ",
      "30,000",
      "0",
      "30,000"
    ],
    [
      " ",
      "2367  ",
      "燿華            ",
      "28,000",
      "0",
      "28,000"
    ],
    [
      " ",
      "3653  ",
      "健策            ",
      "38,000",
      "13,000",
      "25,000"
    ],
    [
      " ",
      "6805  ",
      "富世達          ",
      "32,000",
      "10,000",
      "22,000"
    ],
    [
      " ",
      "8210  ",
      "勤誠            ",
      "20,800",
      "0",
      "20,800"
    ],
    [
      " ",
      "1519  ",
      "華城            ",
      "19,000",
      "657",
      "18,343"
    ],
    [
      " ",
      "3533  ",
      "嘉澤            ",
      "30,000",
      "16,000",
      "14,000"
    ],
    [
      " ",
      "3035  ",
      "智原            ",
      "12,000",
      "0",
      "12,000"
    ],
    [
      " ",
      "2436  ",
      "偉詮電          ",
      "10,000",
      "0",
      "10,000"
    ],
    [
      " ",
      "3545  ",
      "敦泰            ",
      "10,000",
      "0",
      "10,000"
    ],
    [
      " ",
      "4968  ",
      "立積            ",
      "10,000",
      "0",
      "10,000"
    ],
    [
      " ",
      "8261  ",
      "富鼎            ",
      "10,000",
      "0",
      "10,000"
    ],
    [
      " ",
      "2308  ",
      "台達電          ",
      "57,000",
      "48,000",
      "9,000"
    ],
    [
      " ",
      "6533  ",
      "晶心科          ",
      "9,000",
      "0",
      "9,000"
    ],
    [
      " ",
      "3036  ",
      "文曄            ",
      "30,000",
      "24,511",
      "5,489"
    ],
    [
      " ",
      "4961  ",
      "天鈺            ",
      "5,000",
      "0",
      "5,000"
    ],
    [
      " ",
      "6531  ",
      "愛普*           ",
      "5,000",
      "0",
      "5,000"
    ],
    [
      " ",
      "7749  ",
      "意騰-KY         ",
      "5,000",
      "0",
      "5,000"
    ],
    [
      " ",
      "1560  ",
      "中砂            ",
      "5,000",
      "1,000",
      "4,000"
    ],
    [
      " ",
      "6592B ",
      "和潤企業乙特    ",
      "3,000",
      "0",
      "3,000"
    ],
    [
      " ",
      "5269  ",
      "祥碩            ",
      "2,000",
      "0",
      "2,000"
    ],
    [
      " ",
      "6206  ",
      "飛捷            ",
      "1,700",
      "0",
      "1,700"
    ],
    [
      " ",
      "3026  ",
      "禾伸堂          ",
      "1,500",
      "0",
      "1,500"
    ],
    [
      " ",
      "1476  ",
      "儒鴻            ",
      "3,000",
      "1,887",
      "1,113"
    ],
    [
      " ",
      "2884  ",
      "玉山金          ",
      "363,000",
      "3,155,090",
      "-2,792,090"
    ],
    [
      " ",
      "2105  ",
      "正新            ",
      "0",
      "2,693,697",
      "-2,693,697"
    ],
    [
      " ",
      "8021  ",
      "尖點            ",
      "0",
      "2,542,000",
      "-2,542,000"
    ],
    [
      " ",
      "1402  ",
      "遠東新          ",
      "0",
      "2,532,000",
      "-2,532,000"
    ],
    [
      " ",
      "2891  ",
      "中信金          ",
      "464,000",
      "2,747,374",
      "-2,283,374"
    ],
    [
      " ",
      "2603  ",
      "長榮            ",
      "109,000",
      "1,292,067",
      "-1,183,067"
    ],
    [
      " ",
      "3044  ",
      "健鼎            ",
      "0",
      "1,157,501",
      "-1,157,501"
    ],
    [
      " ",
      "2618  ",
      "長榮航          ",
      "0",
      "1,065,525",
      "-1,065,525"
    ],
    [
      " ",
      "5876  ",
      "上海商銀        ",
      "0",
      "812,924",
      "-812,924"
    ],
    [
      " ",
      "2610  ",
      "華航            ",
      "0",
      "811,655",
      "-811,655"
    ],
    [
      " ",
      "2882  ",
      "國泰金          ",
      "254,000",
      "990,070",
      "-736,070"
    ],
    [
      " ",
      "2892  ",
      "第一金          ",
      "0",
      "655,000",
      "-655,000"
    ],
    [
      " ",
      "2887  ",
      "台新新光金      ",
      "2,044,000",
      "2,674,000",
      "-630,000"
    ],
    [
      " ",
      "1605  ",
      "華新            ",
      "0",
      "600,000",
      "-600,000"
    ],
    [
      " ",
      "00984A",
      "主動安聯台灣高息",
      "0",
      "590,000",
      "-590,000"
    ],
    [
      " ",
      "4904  ",
      "遠傳            ",
      "0",
      "579,000",
      "-579,000"
    ],
    [
      " ",
      "2881  ",
      "富邦金          ",
      "264,000",
      "799,535",
      "-535,535"
    ],
    [
      " ",
      "2317  ",
      "鴻海            ",
      "225,000",
      "672,111",
      "-447,111"
    ],
    [
      " ",
      "2327  ",
      "國巨*           ",
      "120,000",
      "563,000",
      "-443,000"
    ],
    [
      " ",
      "1773  ",
      "勝一            ",
      "0",
      "430,200",
      "-430,200"
    ],
    [
      " ",
      "1504  ",
      "東元            ",
      "0",
      "426,695",
      "-426,695"
    ],
    [
      " ",
      "2303  ",
      "聯電            ",
      "1,121,900",
      "1,518,697",
      "-396,797"
    ],
    [
      " ",
      "2883  ",
      "凱基金          ",
      "0",
      "325,000",
      "-325,000"
    ],
    [
      " ",
      "9802  ",
      "鈺齊-KY         ",
      "0",
      "320,000",
      "-320,000"
    ],
    [
      " ",
      "3231  ",
      "緯創            ",
      "0",
      "310,000",
      "-310,000"
    ],
    [
      " ",
      "6005  ",
      "群益證          ",
      "0",
      "290,869",
      "-290,869"
    ],
    [
      " ",
      "9904  ",
      "寶成            ",
      "0",
      "289,351",
      "-289,351"
    ],
    [
      " ",
      "2393  ",
      "億光            ",
      "0",
      "285,857",
      "-285,857"
    ],
    [
      " ",
      "2472  ",
      "立隆電          ",
      "0",
      "251,000",
      "-251,000"
    ],
    [
      " ",
      "3711  ",
      "日月光投控      ",
      "342,000",
      "573,000",
      "-231,000"
    ],
    [
      " ",
      "6239  ",
      "力成            ",
      "0",
      "217,000",
      "-217,000"
    ],
    [
      " ",
      "2615  ",
      "萬海            ",
      "0",
      "190,779",
      "-190,779"
    ],
    [
      " ",
      "2408  ",
      "南亞科          ",
      "1,571,000",
      "1,761,000",
      "-190,000"
    ],
    [
      " ",
      "3702  ",
      "大聯大          ",
      "0",
      "187,000",
      "-187,000"
    ],
    [
      " ",
      "5434  ",
      "崇越            ",
      "0",
      "181,000",
      "-181,000"
    ],
    [
      " ",
      "2609  ",
      "陽明            ",
      "4,600",
      "182,016",
      "-177,416"
    ],
    [
      " ",
      "6831  ",
      "邁科            ",
      "0",
      "172,000",
      "-172,000"
    ],
    [
      " ",
      "1216  ",
      "統一            ",
      "0",
      "164,078",
      "-164,078"
    ],
    [
      " ",
      "4938  ",
      "和碩            ",
      "0",
      "163,000",
      "-163,000"
    ],
    [
      " ",
      "6177  ",
      "達麗            ",
      "0",
      "150,000",
      "-150,000"
    ],
    [
      " ",
      "5871  ",
      "中租-KY         ",
      "0",
      "145,258",
      "-145,258"
    ],
    [
      " ",
      "2324  ",
      "仁寶            ",
      "0",
      "131,000",
      "-131,000"
    ],
    [
      " ",
      "2606  ",
      "裕民            ",
      "0",
      "131,000",
      "-131,000"
    ],
    [
      " ",
      "2637  ",
      "慧洋-KY         ",
      "3,100",
      "124,000",
      "-120,900"
    ],
    [
      " ",
      "3017  ",
      "奇鋐            ",
      "83,000",
      "199,000",
      "-116,000"
    ],
    [
      " ",
      "1303  ",
      "南亞            ",
      "47,000",
      "155,677",
      "-108,677"
    ],
    [
      " ",
      "2880  ",
      "華南金          ",
      "10,000",
      "118,000",
      "-108,000"
    ],
    [
      " ",
      "6415  ",
      "矽力*-KY        ",
      "0",
      "106,000",
      "-106,000"
    ],
    [
      " ",
      "4736  ",
      "泰博            ",
      "0",
      "100,000",
      "-100,000"
    ],
    [
      " ",
      "2312  ",
      "金寶            ",
      "0",
      "94,000",
      "-94,000"
    ],
    [
      " ",
      "2356  ",
      "英業達          ",
      "0",
      "93,000",
      "-93,000"
    ],
    [
      " ",
      "2404  ",
      "漢唐            ",
      "0",
      "89,000",
      "-89,000"
    ],
    [
      " ",
      "4967  ",
      "十銓            ",
      "0",
      "86,000",
      "-86,000"
    ],
    [
      " ",
      "2382  ",
      "廣達            ",
      "65,000",
      "139,273",
      "-74,273"
    ],
    [
      " ",
      "3045  ",
      "台灣大          ",
      "0",
      "70,000",
      "-70,000"
    ],
    [
      " ",
      "6781  ",
      "AES-KY          ",
      "0",
      "67,000",
      "-67,000"
    ],
    [
      " ",
      "3042  ",
      "晶技            ",
      "0",
      "64,000",
      "-64,000"
    ],
    [
      " ",
      "4763  ",
      "材料*-KY        ",
      "0",
      "56,786",
      "-56,786"
    ],
    [
      " ",
      "3715  ",
      "定穎投控        ",
      "0",
      "51,000",
      "-51,000"
    ],
    [
      " ",
      "6278  ",
      "台表科          ",
      "0",
      "50,000",
      "-50,000"
    ],
    [
      " ",
      "9921  ",
      "巨大            ",
      "0",
      "50,000",
      "-50,000"
    ],
    [
      " ",
      "3443  ",
      "創意            ",
      "8,000",
      "57,000",
      "-49,000"
    ],
    [
      " ",
      "6670  ",
      "復盛應用        ",
      "0",
      "48,771",
      "-48,771"
    ],
    [
      " ",
      "5880  ",
      "合庫金          ",
      "0",
      "48,419",
      "-48,419"
    ],
    [
      " ",
      "2379  ",
      "瑞昱            ",
      "5,000",
      "53,000",
      "-48,000"
    ],
    [
      " ",
      "1102  ",
      "亞泥            ",
      "0",
      "47,646",
      "-47,646"
    ],
    [
      " ",
      "2912  ",
      "統一超          ",
      "0",
      "44,142",
      "-44,142"
    ],
    [
      " ",
      "8112  ",
      "至上            ",
      "0",
      "42,008",
      "-42,008"
    ],
    [
      " ",
      "6257  ",
      "矽格            ",
      "0",
      "41,000",
      "-41,000"
    ],
    [
      " ",
      "8070  ",
      "長華*           ",
      "0",
      "40,000",
      "-40,000"
    ],
    [
      " ",
      "2458  ",
      "義隆            ",
      "20,000",
      "59,723",
      "-39,723"
    ],
    [
      " ",
      "2409  ",
      "友達            ",
      "0",
      "38,000",
      "-38,000"
    ],
    [
      " ",
      "2455  ",
      "全新            ",
      "0",
      "38,000",
      "-38,000"
    ],
    [
      " ",
      "2467  ",
      "志聖            ",
      "0",
      "38,000",
      "-38,000"
    ],
    [
      " ",
      "6446  ",
      "藥華藥          ",
      "1,000",
      "38,000",
      "-37,000"
    ],
    [
      " ",
      "6285  ",
      "啟碁            ",
      "0",
      "36,000",
      "-36,000"
    ],
    [
      " ",
      "2801  ",
      "彰銀            ",
      "1,000",
      "36,343",
      "-35,343"
    ],
    [
      " ",
      "1810  ",
      "和成            ",
      "0",
      "31,463",
      "-31,463"
    ],
    [
      " ",
      "2834  ",
      "臺企銀          ",
      "0",
      "29,779",
      "-29,779"
    ],
    [
      " ",
      "2542  ",
      "興富發          ",
      "0",
      "27,000",
      "-27,000"
    ],
    [
      " ",
      "6196  ",
      "帆宣            ",
      "0",
      "25,000",
      "-25,000"
    ],
    [
      " ",
      "1907  ",
      "永豐餘          ",
      "0",
      "20,006",
      "-20,006"
    ],
    [
      " ",
      "4958  ",
      "臻鼎-KY         ",
      "0",
      "19,000",
      "-19,000"
    ],
    [
      " ",
      "2727  ",
      "王品            ",
      "0",
      "17,507",
      "-17,507"
    ],
    [
      " ",
      "8016  ",
      "矽創            ",
      "10,000",
      "27,000",
      "-17,000"
    ],
    [
      " ",
      "3034  ",
      "聯詠            ",
      "5,000",
      "19,962",
      "-14,962"
    ],
    [
      " ",
      "2474  ",
      "可成            ",
      "1,100",
      "16,034",
      "-14,934"
    ],
    [
      " ",
      "2504  ",
      "國產            ",
      "0",
      "14,038",
      "-14,038"
    ],
    [
      " ",
      "1608  ",
      "華榮            ",
      "0",
      "13,824",
      "-13,824"
    ],
    [
      " ",
      "2812  ",
      "台中銀          ",
      "0",
      "12,874",
      "-12,874"
    ],
    [
      " ",
      "2360  ",
      "致茂            ",
      "99,000",
      "111,659",
      "-12,659"
    ],
    [
      " ",
      "3481  ",
      "群創            ",
      "14,100",
      "26,000",
      "-11,900"
    ],
    [
      " ",
      "6505  ",
      "台塑化          ",
      "0",
      "11,864",
      "-11,864"
    ],
    [
      " ",
      "2451  ",
      "創見            ",
      "1,500",
      "13,000",
      "-11,500"
    ],
    [
      " ",
      "2539  ",
      "櫻花建          ",
      "0",
      "11,091",
      "-11,091"
    ],
    [
      " ",
      "2889  ",
      "國票金          ",
      "0",
      "11,000",
      "-11,000"
    ],
    [
      " ",
      "3376  ",
      "新日興          ",
      "0",
      "11,000",
      "-11,000"
    ],
    [
      " ",
      "6191  ",
      "精成科          ",
      "0",
      "10,000",
      "-10,000"
    ],
    [
      " ",
      "1210  ",
      "大成            ",
      "0",
      "9,000",
      "-9,000"
    ],
    [
      " ",
      "2845  ",
      "遠東銀          ",
      "0",
      "9,000",
      "-9,000"
    ],
    [
      " ",
      "2633  ",
      "台灣高鐵        ",
      "0",
      "8,682",
      "-8,682"
    ],
    [
      " ",
      "2206  ",
      "三陽工業        ",
      "0",
      "8,677",
      "-8,677"
    ],
    [
      " ",
      "6176  ",
      "瑞儀            ",
      "0",
      "8,202",
      "-8,202"
    ],
    [
      " ",
      "1477  ",
      "聚陽            ",
      "0",
      "8,039",
      "-8,039"
    ],
    [
      " ",
      "2357  ",
      "華碩            ",
      "0",
      "7,689",
      "-7,689"
    ],
    [
      " ",
      "2204  ",
      "中華            ",
      "0",
      "7,658",
      "-7,658"
    ],
    [
      " ",
      "2006  ",
      "東和鋼鐵        ",
      "0",
      "7,488",
      "-7,488"
    ],
    [
      " ",
      "9910  ",
      "豐泰            ",
      "0",
      "7,358",
      "-7,358"
    ],
    [
      " ",
      "1101  ",
      "台泥            ",
      "0",
      "6,000",
      "-6,000"
    ],
    [
      " ",
      "9939  ",
      "宏全            ",
      "7,000",
      "13,000",
      "-6,000"
    ],
    [
      " ",
      "2371  ",
      "大同            ",
      "5,300",
      "11,000",
      "-5,700"
    ],
    [
      " ",
      "2059  ",
      "川湖            ",
      "0",
      "5,000",
      "-5,000"
    ],
    [
      " ",
      "3450  ",
      "聯鈞            ",
      "0",
      "5,000",
      "-5,000"
    ],
    [
      " ",
      "3029  ",
      "零壹            ",
      "0",
      "4,798",
      "-4,798"
    ],
    [
      " ",
      "3008  ",
      "大立光          ",
      "0",
      "4,257",
      "-4,257"
    ],
    [
      " ",
      "2353  ",
      "宏碁            ",
      "0",
      "4,000",
      "-4,000"
    ],
    [
      " ",
      "2103  ",
      "台橡            ",
      "0",
      "3,000",
      "-3,000"
    ],
    [
      " ",
      "2208  ",
      "台船            ",
      "0",
      "3,000",
      "-3,000"
    ],
    [
      " ",
      "2634  ",
      "漢翔            ",
      "0",
      "3,000",
      "-3,000"
    ],
    [
      " ",
      "3023  ",
      "信邦            ",
      "0",
      "3,000",
      "-3,000"
    ],
    [
      " ",
      "6139  ",
      "亞翔            ",
      "0",
      "3,000",
      "-3,000"
    ],
    [
      " ",
      "6890  ",
      "來億-KY         ",
      "0",
      "3,000",
      "-3,000"
    ],
    [
      " ",
      "3033  ",
      "威健            ",
      "0",
      "2,125",
      "-2,125"
    ],
    [
      " ",
      "1503  ",
      "士電            ",
      "0",
      "2,000",
      "-2,000"
    ],
    [
      " ",
      "2395  ",
      "研華            ",
      "0",
      "2,000",
      "-2,000"
    ],
    [
      " ",
      "2498  ",
      "宏達電          ",
      "0",
      "2,000",
      "-2,000"
    ],
    [
      " ",
      "3413  ",
      "京鼎            ",
      "0",
      "2,000",
      "-2,000"
    ],
    [
      " ",
      "6414  ",
      "樺漢            ",
      "0",
      "2,000",
      "-2,000"
    ],
    [
      " ",
      "7765  ",
      "中華資安        ",
      "0",
      "1,914",
      "-1,914"
    ],
    [
      " ",
      "1795  ",
      "美時            ",
      "0",
      "1,910",
      "-1,910"
    ],
    [
      " ",
      "1319  ",
      "東陽            ",
      "0",
      "1,845",
      "-1,845"
    ],
    [
      " ",
      "8464  ",
      "億豐            ",
      "0",
      "1,833",
      "-1,833"
    ],
    [
      " ",
      "3209  ",
      "全科            ",
      "0",
      "1,486",
      "-1,486"
    ],
    [
      " ",
      "1522  ",
      "堤維西          ",
      "0",
      "1,360",
      "-1,360"
    ],
    [
      " ",
      "1532  ",
      "勤美            ",
      "0",
      "1,340",
      "-1,340"
    ],
    [
      " ",
      "1513  ",
      "中興電          ",
      "0",
      "1,188",
      "-1,188"
    ],
    [
      " ",
      "2852  ",
      "第一保          ",
      "0",
      "1,131",
      "-1,131"
    ],
    [
      " ",
      "1590  ",
      "亞德客-KY       ",
      "0",
      "1,000",
      "-1,000"
    ],
    [
      " ",
      "2201  ",
      "裕隆            ",
      "0",
      "1,000",
      "-1,000"
    ],
    [
      " ",
      "2354  ",
      "鴻準            ",
      "0",
      "1,000",
      "-1,000"
    ],
    [
      " ",
      "2362  ",
      "藍天            ",
      "0",
      "1,000",
      "-1,000"
    ],
    [
      " ",
      "2492  ",
      "華新科          ",
      "0",
      "1,000",
      "-1,000"
    ],
    [
      " ",
      "2838  ",
      "聯邦銀          ",
      "0",
      "1,000",
      "-1,000"
    ],
    [
      " ",
      "6592  ",
      "和潤企業        ",
      "0",
      "1,000",
      "-1,000"
    ],
    [
      " ",
      "6691  ",
      "洋基工程        ",
      "0",
      "1,000",
      "-1,000"
    ],
    [
      " ",
      "6789  ",
      "采鈺            ",
      "0",
      "1,000",
      "-1,000"
    ],
    [
      " ",
      "8131  ",
      "福懋科          ",
      "0",
      "1,000",
      "-1,000"
    ],
    [
      " ",
      "8422  ",
      "可寧衛*         ",
      "0",
      "1,000",
      "-1,000"
    ],
    [
      " ",
      "9933  ",
      "中鼎            ",
      "0",
      "1,000",
      "-1,000"
    ],
    [
      " ",
      "6944  ",
      "兆聯實業        ",
      "0",
      "834",
      "-834"
    ],
    [
      " ",
      "3014  ",
      "聯陽            ",
      "0",
      "716",
      "-716"
    ],
    [
      " ",
      "4720  ",
      "德淵            ",
      "0",
      "503",
      "-503"
    ],
    [
      " ",
      "3038  ",
      "全台            ",
      "0",
      "481",
      "-481"
    ],
    [
      " ",
      "9924  ",
      "福興            ",
      "0",
      "444",
      "-444"
    ],
    [
      " ",
      "2439  ",
      "美律            ",
      "1,700",
      "2,133",
      "-433"
    ],
    [
      " ",
      "2527  ",
      "宏璟            ",
      "0",
      "325",
      "-325"
    ],
    [
      " ",
      "3592  ",
      "瑞鼎            ",
      "0",
      "278",
      "-278"
    ],
    [
      " ",
      "1558  ",
      "伸興            ",
      "0",
      "193",
      "-193"
    ],
    [
      " ",
      "6754  ",
      "匯僑設計        ",
      "0",
      "70",
      "-70"
    ],
    [
      " ",
      "6669  ",
      "緯穎            ",
      "16,000",
      "16,000",
      "0"
    ]
  ],
  "notes": [
    "投信表示本國投資信託基金。",
    "＊表示該證券今日有鉅額交易。",
    "本統計資訊含一般、零股、盤後定價、鉅額，不含拍賣、標購。",
    "本資訊以當日原始成交情形統計，不以證券商申報錯帳、更正帳號等調整後資料統計。",
    "ETF證券代號第六碼為K、M、S、C者，表示該ETF以外幣交易。"
  ],
  "hints": "單位：股",
  "total": 220
}