{
  "stat": "OK",
  "date": "20260429",
  "title": "115年04月29日 投信買賣超彙總表",
  "fields": [
    "",
    "證券代號",
    "證券名稱",
    "買進股數",
    "賣出股數",
    "買賣超股數"
  ],
  "data": [
    [
      " ",
      "4958  ",
      "臻鼎-KY         ",
      "4,961,000",
      "451,890",
      "4,509,110"
    ],
    [
      " ",
      "2337  ",
      "旺宏            ",
      "3,796,000",
      "1,433,000",
      "2,363,000"
    ],
    [
      " ",
      "2610  ",
      "華航            ",
      "3,533,000",
      "1,262,000",
      "2,271,000"
    ],
    [
      " ",
      "2408  ",
      "南亞科          ",
      "2,083,000",
      "3,583",
      "2,079,417"
    ],
    [
      " ",
      "2027  ",
      "大成鋼          ",
      "1,725,000",
      "205,000",
      "1,520,000"
    ],
    [
      " ",
      "2454  ",
      "聯發科          ",
      "1,463,000",
      "88,820",
      "1,374,180"
    ],
    [
      " ",
      "2330  ",
      "台積電          ",
      "1,109,470",
      "107,336",
      "1,002,134"
    ],
    [
      " ",
      "2618  ",
      "長榮航          ",
      "2,031,000",
      "1,192,000",
      "839,000"
    ],
    [
      " ",
      "3189  ",
      "景碩            ",
      "1,159,000",
      "376,480",
      "782,520"
    ],
    [
      " ",
      "2317  ",
      "鴻海            ",
      "860,000",
      "81,392",
      "778,608"
    ],
    [
      " ",
      "3711  ",
      "日月光投控      ",
      "1,202,000",
      "520,963",
      "681,037"
    ],
    [
      " ",
      "00988A",
      "主動統一全球創新",
      "630,000",
      "0",
      "630,000"
    ],
    [
      " ",
      "2883  ",
      "凱基金          ",
      "1,398,000",
      "867,000",
      "531,000"
    ],
    [
      " ",
      "6285  ",
      "啟碁            ",
      "533,000",
      "26,000",
      "507,000"
    ],
    [
      " ",
      "8028  ",
      "昇陽半導體      ",
      "493,000",
      "0",
      "493,000"
    ],
    [
      " ",
      "2308  ",
      "台達電          ",
      "417,000",
      "70,042",
      "346,958"
    ],
    [
      " ",
      "8996  ",
      "高力            ",
      "469,000",
      "123,000",
      "346,000"
    ],
    [
      " ",
      "3665  ",
      "貿聯-KY         ",
      "391,000",
      "55,000",
      "336,000"
    ],
    [
      " ",
      "00997A",
      "主動群益美國增長",
      "300,000",
      "0",
      "300,000"
    ],
    [
      " ",
      "1307  ",
      "三芳            ",
      "300,000",
      "0",
      "300,000"
    ],
    [
      " ",
      "2031  ",
      "新光鋼          ",
      "300,000",
      "0",
      "300,000"
    ],
    [
      " ",
      "8046  ",
      "南電            ",
      "363,000",
      "68,000",
      "295,000"
    ],
    [
      " ",
      "1303  ",
      "南亞            ",
      "284,000",
      "6,000",
      "278,000"
    ],
    [
      " ",
      "2486  ",
      "一詮            ",
      "277,000",
      "0",
      "277,000"
    ],
    [
      " ",
      "1590  ",
      "亞德客-KY       ",
      "294,001",
      "18,487",
      "275,514"
    ],
    [
      " ",
      "9938  ",
      "百和            ",
      "229,000",
      "0",
      "229,000"
    ],
    [
      " ",
      "2049  ",
      "上銀            ",
      "209,000",
      "1,000",
      "208,000"
    ],
    [
      " ",
      "6669  ",
      "緯穎            ",
      "230,000",
      "27,350",
      "202,650"
    ],
    [
      " ",
      "1612  ",
      "宏泰            ",
      "200,000",
      "0",
      "200,000"
    ],
    [
      " ",
      "6189  ",
      "豐藝            ",
      "200,000",
      "0",
      "200,000"
    ],
    [
      " ",
      "2204  ",
      "中華            ",
      "179,000",
      "0",
      "179,000"
    ],
    [
      " ",
      "2360  ",
      "致茂            ",
      "181,000",
      "2,032",
      "178,968"
    ],
    [
      " ",
      "4746  ",
      "台耀            ",
      "156,000",
      "0",
      "156,000"
    ],
    [
      " ",
      "1560  ",
      "中砂            ",
      "152,000",
      "1,000",
      "151,000"
    ],
    [
      " ",
      "3036  ",
      "文曄            ",
      "338,000",
      "187,000",
      "151,000"
    ],
    [
      " ",
      "7769  ",
      "鴻勁            ",
      "181,300",
      "35,051",
      "146,249"
    ],
    [
      " ",
      "2059  ",
      "川湖            ",
      "136,900",
      "1,283",
      "135,617"
    ],
    [
      " ",
      "5534  ",
      "長虹            ",
      "130,000",
      "0",
      "130,000"
    ],
    [
      " ",
      "9802  ",
      "鈺齊-KY         ",
      "129,000",
      "0",
      "129,000"
    ],
    [
      " ",
      "6768  ",
      "志強-KY         ",
      "128,000",
      "0",
      "128,000"
    ],
    [
      " ",
      "009803",
      "玉山市值動能50  ",
      "120,000",
      "0",
      "120,000"
    ],
    [
      " ",
      "8210  ",
      "勤誠            ",
      "177,000",
      "60,000",
      "117,000"
    ],
    [
      " ",
      "9910  ",
      "豐泰            ",
      "116,000",
      "1,000",
      "115,000"
    ],
    [
      " ",
      "6830  ",
      "汎銓            ",
      "107,000",
      "0",
      "107,000"
    ],
    [
      " ",
      "9941  ",
      "裕融            ",
      "104,000",
      "1,000",
      "103,000"
    ],
    [
      " ",
      "2480  ",
      "敦陽科          ",
      "100,000",
      "0",
      "100,000"
    ],
    [
      " ",
      "3583  ",
      "辛耘            ",
      "87,000",
      "1,000",
      "86,000"
    ],
    [
      " ",
      "2072  ",
      "世紀風電        ",
      "78,000",
      "0",
      "78,000"
    ],
    [
      " ",
      "2731  ",
      "雄獅            ",
      "75,000",
      "0",
      "75,000"
    ],
    [
      " ",
      "1717  ",
      "長興            ",
      "80,000",
      "6,483",
      "73,517"
    ],
    [
      " ",
      "2753  ",
      "八方雲集        ",
      "70,000",
      "0",
      "70,000"
    ],
    [
      " ",
      "2548  ",
      "華固            ",
      "69,000",
      "0",
      "69,000"
    ],
    [
      " ",
      "3017  ",
      "奇鋐            ",
      "92,000",
      "31,161",
      "60,839"
    ],
    [
      " ",
      "3533  ",
      "嘉澤            ",
      "73,000",
      "20,298",
      "52,702"
    ],
    [
      " ",
      "2892  ",
      "第一金          ",
      "100,000",
      "52,000",
      "48,000"
    ],
    [
      " ",
      "2727  ",
      "王品            ",
      "46,000",
      "0",
      "46,000"
    ],
    [
      " ",
      "6139  ",
      "亞翔            ",
      "45,000",
      "360",
      "44,640"
    ],
    [
      " ",
      "5234  ",
      "達興材料        ",
      "131,000",
      "93,000",
      "38,000"
    ],
    [
      " ",
      "3592  ",
      "瑞鼎            ",
      "36,000",
      "0",
      "36,000"
    ],
    [
      " ",
      "2476  ",
      "鉅祥            ",
      "25,000",
      "0",
      "25,000"
    ],
    [
      " ",
      "6670  ",
      "復盛應用        ",
      "36,000",
      "14,000",
      "22,000"
    ],
    [
      " ",
      "6515  ",
      "穎崴            ",
      "23,000",
      "2,216",
      "20,784"
    ],
    [
      " ",
      "1477  ",
      "聚陽            ",
      "47,000",
      "32,000",
      "15,000"
    ],
    [
      " ",
      "6770  ",
      "力積電          ",
      "18,000",
      "7,000",
      "11,000"
    ],
    [
      " ",
      "2393  ",
      "億光            ",
      "129,000",
      "120,000",
      "9,000"
    ],
    [
      " ",
      "2455  ",
      "全新            ",
      "8,000",
      "0",
      "8,000"
    ],
    [
      " ",
      "1476  ",
      "儒鴻            ",
      "6,000",
      "0",
      "6,000"
    ],
    [
      " ",
      "2492  ",
      "華新科          ",
      "4,000",
      "0",
      "4,000"
    ],
    [
      " ",
      "6789  ",
      "采鈺            ",
      "4,000",
      "0",
      "4,000"
    ],
    [
      " ",
      "2354  ",
      "鴻準            ",
      "5,000",
      "2,000",
      "3,000"
    ],
    [
      " ",
      "5269  ",
      "祥碩            ",
      "2,000",
      "385",
      "1,615"
    ],
    [
      " ",
      "2409  ",
      "友達            ",
      "33,000",
      "31,400",
      "1,600"
    ],
    [
      " ",
      "3706  ",
      "神達            ",
      "5,000",
      "3,638",
      "1,362"
    ],
    [
      " ",
      "6191  ",
      "精成科          ",
      "1,000",
      "0",
      "1,000"
    ],
    [
      " ",
      "3008  ",
      "大立光          ",
      "1,000",
      "441",
      "559"
    ],
    [
      " ",
      "2887  ",
      "台新新光金      ",
      "600,000",
      "12,998,000",
      "-12,398,000"
    ],
    [
      " ",
      "2882  ",
      "國泰金          ",
      "300,000",
      "12,217,000",
      "-11,917,000"
    ],
    [
      " ",
      "2344  ",
      "華邦電          ",
      "188,000",
      "8,834,537",
      "-8,646,537"
    ],
    [
      " ",
      "2891  ",
      "中信金          ",
      "2,641,000",
      "8,070,000",
      "-5,429,000"
    ],
    [
      " ",
      "2884  ",
      "玉山金          ",
      "200,000",
      "5,561,000",
      "-5,361,000"
    ],
    [
      " ",
      "2303  ",
      "聯電            ",
      "1,599,000",
      "6,627,740",
      "-5,028,740"
    ],
    [
      " ",
      "2449  ",
      "京元電子        ",
      "263,000",
      "5,137,423",
      "-4,874,423"
    ],
    [
      " ",
      "2324  ",
      "仁寶            ",
      "60,000",
      "4,145,000",
      "-4,085,000"
    ],
    [
      " ",
      "2880  ",
      "華南金          ",
      "200,000",
      "4,055,000",
      "-3,855,000"
    ],
    [
      " ",
      "3702  ",
      "大聯大          ",
      "9,000",
      "3,331,000",
      "-3,322,000"
    ],
    [
      " ",
      "2353  ",
      "宏碁            ",
      "16,000",
      "2,900,000",
      "-2,884,000"
    ],
    [
      " ",
      "1301  ",
      "台塑            ",
      "0",
      "2,857,000",
      "-2,857,000"
    ],
    [
      " ",
      "1216  ",
      "統一            ",
      "0",
      "2,654,000",
      "-2,654,000"
    ],
    [
      " ",
      "2327  ",
      "國巨*           ",
      "2,192,000",
      "4,676,363",
      "-2,484,363"
    ],
    [
      " ",
      "2885  ",
      "元大金          ",
      "400,000",
      "2,805,000",
      "-2,405,000"
    ],
    [
      " ",
      "4904  ",
      "遠傳            ",
      "353,000",
      "2,536,000",
      "-2,183,000"
    ],
    [
      " ",
      "6005  ",
      "群益證          ",
      "0",
      "2,074,000",
      "-2,074,000"
    ],
    [
      " ",
      "6278  ",
      "台表科          ",
      "0",
      "1,637,000",
      "-1,637,000"
    ],
    [
      " ",
      "9904  ",
      "寶成            ",
      "0",
      "1,493,000",
      "-1,493,000"
    ],
    [
      " ",
      "2347  ",
      "聯強            ",
      "7,000",
      "1,365,000",
      "-1,358,000"
    ],
    [
      " ",
      "2313  ",
      "華通            ",
      "204,000",
      "1,523,000",
      "-1,319,000"
    ],
    [
      " ",
      "2886  ",
      "兆豐金          ",
      "120,000",
      "1,430,000",
      "-1,310,000"
    ],
    [
      " ",
      "2439  ",
      "美律            ",
      "0",
      "1,255,000",
      "-1,255,000"
    ],
    [
      " ",
      "3045  ",
      "台灣大          ",
      "30,000",
      "1,282,216",
      "-1,252,216"
    ],
    [
      " ",
      "6239  ",
      "力成            ",
      "26,000",
      "1,160,685",
      "-1,134,685"
    ],
    [
      " ",
      "2890  ",
      "永豐金          ",
      "400,000",
      "1,365,000",
      "-965,000"
    ],
    [
      " ",
      "2356  ",
      "英業達          ",
      "41,000",
      "807,000",
      "-766,000"
    ],
    [
      " ",
      "6412  ",
      "群電            ",
      "0",
      "765,000",
      "-765,000"
    ],
    [
      " ",
      "2801  ",
      "彰銀            ",
      "0",
      "743,000",
      "-743,000"
    ],
    [
      " ",
      "5388  ",
      "中磊            ",
      "0",
      "716,000",
      "-716,000"
    ],
    [
      " ",
      "2105  ",
      "正新            ",
      "0",
      "680,931",
      "-680,931"
    ],
    [
      " ",
      "6176  ",
      "瑞儀            ",
      "2,000",
      "668,000",
      "-666,000"
    ],
    [
      " ",
      "2451  ",
      "創見            ",
      "3,000",
      "657,630",
      "-654,630"
    ],
    [
      " ",
      "2385  ",
      "群光            ",
      "72,000",
      "722,000",
      "-650,000"
    ],
    [
      " ",
      "2474  ",
      "可成            ",
      "2,000",
      "611,272",
      "-609,272"
    ],
    [
      " ",
      "2481  ",
      "強茂            ",
      "0",
      "570,000",
      "-570,000"
    ],
    [
      " ",
      "6213  ",
      "聯茂            ",
      "0",
      "553,000",
      "-553,000"
    ],
    [
      " ",
      "5876  ",
      "上海商銀        ",
      "0",
      "532,000",
      "-532,000"
    ],
    [
      " ",
      "1319  ",
      "東陽            ",
      "131,000",
      "662,211",
      "-531,211"
    ],
    [
      " ",
      "2603  ",
      "長榮            ",
      "0",
      "530,000",
      "-530,000"
    ],
    [
      " ",
      "2382  ",
      "廣達            ",
      "43,000",
      "572,436",
      "-529,436"
    ],
    [
      " ",
      "4938  ",
      "和碩            ",
      "10,000",
      "529,009",
      "-519,009"
    ],
    [
      " ",
      "1402  ",
      "遠東新          ",
      "0",
      "518,000",
      "-518,000"
    ],
    [
      " ",
      "1210  ",
      "大成            ",
      "0",
      "509,000",
      "-509,000"
    ],
    [
      " ",
      "3042  ",
      "晶技            ",
      "0",
      "490,000",
      "-490,000"
    ],
    [
      " ",
      "2881  ",
      "富邦金          ",
      "1,316,000",
      "1,794,250",
      "-478,250"
    ],
    [
      " ",
      "2912  ",
      "統一超          ",
      "0",
      "475,000",
      "-475,000"
    ],
    [
      " ",
      "2605  ",
      "新興            ",
      "0",
      "463,309",
      "-463,309"
    ],
    [
      " ",
      "3034  ",
      "聯詠            ",
      "23,000",
      "481,887",
      "-458,887"
    ],
    [
      " ",
      "3037  ",
      "欣興            ",
      "1,312,000",
      "1,747,000",
      "-435,000"
    ],
    [
      " ",
      "2301  ",
      "光寶科          ",
      "20,900",
      "434,019",
      "-413,119"
    ],
    [
      " ",
      "4915  ",
      "致伸            ",
      "121,000",
      "521,000",
      "-400,000"
    ],
    [
      " ",
      "8021  ",
      "尖點            ",
      "0",
      "396,000",
      "-396,000"
    ],
    [
      " ",
      "2903  ",
      "遠百            ",
      "0",
      "381,000",
      "-381,000"
    ],
    [
      " ",
      "1513  ",
      "中興電          ",
      "0",
      "379,217",
      "-379,217"
    ],
    [
      " ",
      "2504  ",
      "國產            ",
      "0",
      "364,000",
      "-364,000"
    ],
    [
      " ",
      "5871  ",
      "中租-KY         ",
      "0",
      "362,000",
      "-362,000"
    ],
    [
      " ",
      "2412  ",
      "中華電          ",
      "0",
      "360,000",
      "-360,000"
    ],
    [
      " ",
      "3231  ",
      "緯創            ",
      "44,000",
      "383,511",
      "-339,511"
    ],
    [
      " ",
      "2357  ",
      "華碩            ",
      "22,000",
      "357,182",
      "-335,182"
    ],
    [
      " ",
      "6805  ",
      "富世達          ",
      "3,000",
      "298,000",
      "-295,000"
    ],
    [
      " ",
      "3406  ",
      "玉晶光          ",
      "0",
      "283,000",
      "-283,000"
    ],
    [
      " ",
      "3005  ",
      "神基            ",
      "2,000",
      "281,000",
      "-279,000"
    ],
    [
      " ",
      "0052  ",
      "富邦科技        ",
      "0",
      "274,000",
      "-274,000"
    ],
    [
      " ",
      "3023  ",
      "信邦            ",
      "2,000",
      "269,107",
      "-267,107"
    ],
    [
      " ",
      "1532  ",
      "勤美            ",
      "0",
      "250,000",
      "-250,000"
    ],
    [
      " ",
      "8163  ",
      "達方            ",
      "0",
      "250,000",
      "-250,000"
    ],
    [
      " ",
      "2368  ",
      "金像電          ",
      "162,000",
      "395,602",
      "-233,602"
    ],
    [
      " ",
      "0056  ",
      "元大高股息      ",
      "0",
      "226,000",
      "-226,000"
    ],
    [
      " ",
      "6415  ",
      "矽力*-KY        ",
      "13,000",
      "228,000",
      "-215,000"
    ],
    [
      " ",
      "3044  ",
      "健鼎            ",
      "2,000",
      "214,000",
      "-212,000"
    ],
    [
      " ",
      "00984D",
      "主動聯博全球非投",
      "0",
      "200,000",
      "-200,000"
    ],
    [
      " ",
      "1522  ",
      "堤維西          ",
      "0",
      "200,000",
      "-200,000"
    ],
    [
      " ",
      "3661  ",
      "世芯-KY         ",
      "5,000",
      "202,000",
      "-197,000"
    ],
    [
      " ",
      "2206  ",
      "三陽工業        ",
      "0",
      "180,000",
      "-180,000"
    ],
    [
      " ",
      "3010  ",
      "華立            ",
      "0",
      "179,000",
      "-179,000"
    ],
    [
      " ",
      "1215  ",
      "卜蜂            ",
      "0",
      "177,000",
      "-177,000"
    ],
    [
      " ",
      "1102  ",
      "亞泥            ",
      "0",
      "167,264",
      "-167,264"
    ],
    [
      " ",
      "8422  ",
      "可寧衛*         ",
      "0",
      "163,000",
      "-163,000"
    ],
    [
      " ",
      "2006  ",
      "東和鋼鐵        ",
      "0",
      "161,000",
      "-161,000"
    ],
    [
      " ",
      "2395  ",
      "研華            ",
      "3,000",
      "164,000",
      "-161,000"
    ],
    [
      " ",
      "2645  ",
      "長榮航太        ",
      "0",
      "156,000",
      "-156,000"
    ],
    [
      " ",
      "8454  ",
      "富邦媒          ",
      "49,000",
      "194,000",
      "-145,000"
    ],
    [
      " ",
      "5469  ",
      "瀚宇博          ",
      "0",
      "132,000",
      "-132,000"
    ],
    [
      " ",
      "3443  ",
      "創意            ",
      "5,000",
      "134,253",
      "-129,253"
    ],
    [
      " ",
      "6257  ",
      "矽格            ",
      "0",
      "119,123",
      "-119,123"
    ],
    [
      " ",
      "6414  ",
      "樺漢            ",
      "0",
      "106,000",
      "-106,000"
    ],
    [
      " ",
      "00892 ",
      "富邦台灣半導體  ",
      "0",
      "104,000",
      "-104,000"
    ],
    [
      " ",
      "3015  ",
      "全漢            ",
      "0",
      "101,000",
      "-101,000"
    ],
    [
      " ",
      "9907  ",
      "統一實          ",
      "546,000",
      "647,000",
      "-101,000"
    ],
    [
      " ",
      "0050  ",
      "元大台灣50      ",
      "0",
      "100,000",
      "-100,000"
    ],
    [
      " ",
      "1702  ",
      "南僑            ",
      "0",
      "100,000",
      "-100,000"
    ],
    [
      " ",
      "2379  ",
      "瑞昱            ",
      "19,000",
      "116,689",
      "-97,689"
    ],
    [
      " ",
      "6442  ",
      "光聖            ",
      "1,000",
      "95,033",
      "-94,033"
    ],
    [
      " ",
      "2376  ",
      "技嘉            ",
      "3,000",
      "95,000",
      "-92,000"
    ],
    [
      " ",
      "2606  ",
      "裕民            ",
      "99,000",
      "189,000",
      "-90,000"
    ],
    [
      " ",
      "00881 ",
      "國泰台灣科技龍頭",
      "0",
      "85,000",
      "-85,000"
    ],
    [
      " ",
      "2458  ",
      "義隆            ",
      "0",
      "77,836",
      "-77,836"
    ],
    [
      " ",
      "00662 ",
      "富邦NASDAQ      ",
      "0",
      "75,000",
      "-75,000"
    ],
    [
      " ",
      "9939  ",
      "宏全            ",
      "0",
      "75,000",
      "-75,000"
    ],
    [
      " ",
      "2383  ",
      "台光電          ",
      "68,000",
      "140,909",
      "-72,909"
    ],
    [
      " ",
      "2850  ",
      "新產            ",
      "0",
      "67,000",
      "-67,000"
    ],
    [
      " ",
      "2015  ",
      "豐興            ",
      "0",
      "66,000",
      "-66,000"
    ],
    [
      " ",
      "3563  ",
      "牧德            ",
      "0",
      "53,000",
      "-53,000"
    ],
    [
      " ",
      "1519  ",
      "華城            ",
      "0",
      "51,111",
      "-51,111"
    ],
    [
      " ",
      "2404  ",
      "漢唐            ",
      "4,000",
      "55,084",
      "-51,084"
    ],
    [
      " ",
      "4536  ",
      "拓凱            ",
      "0",
      "50,000",
      "-50,000"
    ],
    [
      " ",
      "5880  ",
      "合庫金          ",
      "0",
      "50,000",
      "-50,000"
    ],
    [
      " ",
      "2377  ",
      "微星            ",
      "4,000",
      "51,335",
      "-47,335"
    ],
    [
      " ",
      "1101  ",
      "台泥            ",
      "0",
      "46,000",
      "-46,000"
    ],
    [
      " ",
      "6505  ",
      "台塑化          ",
      "0",
      "42,000",
      "-42,000"
    ],
    [
      " ",
      "4766  ",
      "南寶            ",
      "0",
      "38,000",
      "-38,000"
    ],
    [
      " ",
      "2834  ",
      "臺企銀          ",
      "0",
      "35,000",
      "-35,000"
    ],
    [
      " ",
      "3450  ",
      "聯鈞            ",
      "0",
      "35,000",
      "-35,000"
    ],
    [
      " ",
      "2331  ",
      "精英            ",
      "0",
      "31,000",
      "-31,000"
    ],
    [
      " ",
      "2530  ",
      "華建            ",
      "0",
      "31,000",
      "-31,000"
    ],
    [
      " ",
      "6446  ",
      "藥華藥          ",
      "0",
      "30,840",
      "-30,840"
    ],
    [
      " ",
      "6781  ",
      "AES-KY          ",
      "0",
      "27,110",
      "-27,110"
    ],
    [
      " ",
      "2845  ",
      "遠東銀          ",
      "0",
      "27,000",
      "-27,000"
    ],
    [
      " ",
      "2207  ",
      "和泰車          ",
      "0",
      "22,000",
      "-22,000"
    ],
    [
      " ",
      "1722  ",
      "台肥            ",
      "0",
      "20,000",
      "-20,000"
    ],
    [
      " ",
      "2371  ",
      "大同            ",
      "0",
      "19,262",
      "-19,262"
    ],
    [
      " ",
      "1605  ",
      "華新            ",
      "0",
      "15,931",
      "-15,931"
    ],
    [
      " ",
      "5522  ",
      "遠雄            ",
      "0",
      "15,000",
      "-15,000"
    ],
    [
      " ",
      "2002  ",
      "中鋼            ",
      "0",
      "14,000",
      "-14,000"
    ],
    [
      " ",
      "2609  ",
      "陽明            ",
      "0",
      "12,000",
      "-12,000"
    ],
    [
      " ",
      "2633  ",
      "台灣高鐵        ",
      "0",
      "11,000",
      "-11,000"
    ],
    [
      " ",
      "3481  ",
      "群創            ",
      "42,000",
      "52,955",
      "-10,955"
    ],
    [
      " ",
      "5515  ",
      "建國            ",
      "0",
      "10,000",
      "-10,000"
    ],
    [
      " ",
      "8112  ",
      "至上            ",
      "0",
      "10,000",
      "-10,000"
    ],
    [
      " ",
      "1905  ",
      "華紙            ",
      "0",
      "9,000",
      "-9,000"
    ],
    [
      " ",
      "2388  ",
      "威盛            ",
      "0",
      "9,000",
      "-9,000"
    ],
    [
      " ",
      "2542  ",
      "興富發          ",
      "0",
      "9,000",
      "-9,000"
    ],
    [
      " ",
      "3653  ",
      "健策            ",
      "3,000",
      "11,426",
      "-8,426"
    ],
    [
      " ",
      "4906  ",
      "正文            ",
      "0",
      "8,000",
      "-8,000"
    ],
    [
      " ",
      "7722  ",
      "LINEPAY         ",
      "0",
      "8,000",
      "-8,000"
    ],
    [
      " ",
      "2355  ",
      "敬鵬            ",
      "0",
      "7,000",
      "-7,000"
    ],
    [
      " ",
      "2812  ",
      "台中銀          ",
      "0",
      "7,000",
      "-7,000"
    ],
    [
      " ",
      "9945  ",
      "潤泰新          ",
      "0",
      "7,000",
      "-7,000"
    ],
    [
      " ",
      "2345  ",
      "智邦            ",
      "183,000",
      "189,272",
      "-6,272"
    ],
    [
      " ",
      "2208  ",
      "台船            ",
      "0",
      "6,000",
      "-6,000"
    ],
    [
      " ",
      "2485  ",
      "兆赫            ",
      "0",
      "6,000",
      "-6,000"
    ],
    [
      " ",
      "2634  ",
      "漢翔            ",
      "0",
      "6,000",
      "-6,000"
    ],
    [
      " ",
      "8464  ",
      "億豐            ",
      "0",
      "6,000",
      "-6,000"
    ],
    [
      " ",
      "3006  ",
      "晶豪科          ",
      "0",
      "5,000",
      "-5,000"
    ],
    [
      " ",
      "3715  ",
      "定穎投控        ",
      "0",
      "5,000",
      "-5,000"
    ],
    [
      " ",
      "1229  ",
      "聯華            ",
      "0",
      "4,000",
      "-4,000"
    ],
    [
      " ",
      "2352  ",
      "佳世達          ",
      "0",
      "4,000",
      "-4,000"
    ],
    [
      " ",
      "3209  ",
      "全科            ",
      "0",
      "4,000",
      "-4,000"
    ],
    [
      " ",
      "1582  ",
      "信錦            ",
      "0",
      "3,000",
      "-3,000"
    ],
    [
      " ",
      "1609  ",
      "大亞            ",
      "0",
      "3,000",
      "-3,000"
    ],
    [
      " ",
      "2351  ",
      "順德            ",
      "0",
      "3,000",
      "-3,000"
    ],
    [
      " ",
      "2399  ",
      "映泰            ",
      "0",
      "3,000",
      "-3,000"
    ],
    [
      " ",
      "2419  ",
      "仲琦            ",
      "0",
      "3,000",
      "-3,000"
    ],
    [
      " ",
      "2915  ",
      "潤泰全          ",
      "0",
      "3,000",
      "-3,000"
    ],
    [
      " ",
      "3645  ",
      "達邁            ",
      "0",
      "3,000",
      "-3,000"
    ],
    [
      " ",
      "8215  ",
      "明基材          ",
      "0",
      "3,000",
      "-3,000"
    ],
    [
      " ",
      "9933  ",
      "中鼎            ",
      "0",
      "3,000",
      "-3,000"
    ],
    [
      " ",
      "1504  ",
      "東元            ",
      "0",
      "2,741",
      "-2,741"
    ],
    [
      " ",
      "3035  ",
      "智原            ",
      "0",
      "2,610",
      "-2,610"
    ],
    [
      " ",
      "2472  ",
      "立隆電          ",
      "0",
      "2,348",
      "-2,348"
    ],
    [
      " ",
      "1528  ",
      "恩德            ",
      "0",
      "2,000",
      "-2,000"
    ],
    [
      " ",
      "1597  ",
      "直得            ",
      "0",
      "2,000",
      "-2,000"
    ],
    [
      " ",
      "2467  ",
      "志聖            ",
      "40,000",
      "42,000",
      "-2,000"
    ],
    [
      " ",
      "2615  ",
      "萬海            ",
      "0",
      "2,000",
      "-2,000"
    ],
    [
      " ",
      "2838  ",
      "聯邦銀          ",
      "0",
      "2,000",
      "-2,000"
    ],
    [
      " ",
      "2855  ",
      "統一證          ",
      "0",
      "2,000",
      "-2,000"
    ],
    [
      " ",
      "3031  ",
      "佰鴻            ",
      "0",
      "2,000",
      "-2,000"
    ],
    [
      " ",
      "3167  ",
      "大量            ",
      "0",
      "2,000",
      "-2,000"
    ],
    [
      " ",
      "4720  ",
      "德淵            ",
      "0",
      "2,000",
      "-2,000"
    ],
    [
      " ",
      "4763  ",
      "材料*-KY        ",
      "0",
      "2,000",
      "-2,000"
    ],
    [
      " ",
      "4956  ",
      "光鋐            ",
      "0",
      "2,000",
      "-2,000"
    ],
    [
      " ",
      "4977  ",
      "眾達-KY         ",
      "0",
      "2,000",
      "-2,000"
    ],
    [
      " ",
      "6282  ",
      "康舒            ",
      "0",
      "2,000",
      "-2,000"
    ],
    [
      " ",
      "6672  ",
      "騰輝電子-KY     ",
      "0",
      "2,000",
      "-2,000"
    ],
    [
      " ",
      "8271  ",
      "宇瞻            ",
      "0",
      "2,000",
      "-2,000"
    ],
    [
      " ",
      "1707  ",
      "葡萄王          ",
      "0",
      "1,000",
      "-1,000"
    ],
    [
      " ",
      "1735  ",
      "日勝化          ",
      "0",
      "1,000",
      "-1,000"
    ],
    [
      " ",
      "2211  ",
      "長榮鋼          ",
      "0",
      "1,000",
      "-1,000"
    ],
    [
      " ",
      "2243  ",
      "宏旭-KY         ",
      "0",
      "1,000",
      "-1,000"
    ],
    [
      " ",
      "2305  ",
      "全友            ",
      "0",
      "1,000",
      "-1,000"
    ],
    [
      " ",
      "2515  ",
      "中工            ",
      "0",
      "1,000",
      "-1,000"
    ],
    [
      " ",
      "2889  ",
      "國票金          ",
      "0",
      "1,000",
      "-1,000"
    ],
    [
      " ",
      "3026  ",
      "禾伸堂          ",
      "2,000",
      "3,000",
      "-1,000"
    ],
    [
      " ",
      "3376  ",
      "新日興          ",
      "0",
      "1,000",
      "-1,000"
    ],
    [
      " ",
      "3708  ",
      "上緯投控        ",
      "0",
      "1,000",
      "-1,000"
    ],
    [
      " ",
      "4739  ",
      "康普            ",
      "0",
      "1,000",
      "-1,000"
    ],
    [
      " ",
      "4949  ",
      "有成精密        ",
      "0",
      "1,000",
      "-1,000"
    ],
    [
      " ",
      "5484  ",
      "慧友            ",
      "0",
      "1,000",
      "-1,000"
    ],
    [
      " ",
      "9921  ",
      "巨大            ",
      "0",
      "1,000",
      "-1,000"
    ],
    [
      " ",
      "9958  ",
      "世紀鋼          ",
      "0",
      "1,000",
      "-1,000"
    ],
    [
      " ",
      "6531  ",
      "愛普*           ",
      "3,000",
      "3,735",
      "-735"
    ],
    [
      " ",
      "3019  ",
      "亞光            ",
      "0",
      "396",
      "-396"
    ],
    [
      " ",
      "5434  ",
      "崇越            ",
      "1,000",
      "1,349",
      "-349"
    ],
    [
      " ",
      "2375  ",
      "凱美            ",
      "0",
      "318",
      "-318"
    ],
    [
      " ",
      "6196  ",
      "帆宣            ",
      "0",
      "171",
      "-171"
    ],
    [
      " ",
      "1503  ",
      "士電            ",
      "0",
      "157",
      "-157"
    ],
    [
      " ",
      "6449  ",
      "鈺邦            ",
      "0",
      "117",
      "-117"
    ],
    [
      " ",
      "6409  ",
      "旭隼            ",
      "0",
      "35",
      "-35"
    ]
  ],
  "notes": [
    "投信表示本國投資信託基金。",
    "＊表示該證券今日有鉅額交易。",
    "本統計資訊含一般、零股、盤後定價、鉅額，不含拍賣、標購。",
    "本資訊以當日原始成交情形統計，不以證券商申報錯帳、更正帳號等調整後資料統計。",
    "ETF證券代號第六碼為K、M、S、C者，表示該ETF以外幣交易。"
  ],
  "hints": "單位：股",
  "total": 274
}